topsis_aarushi/__init__.py
topsis_aarushi/topsis.py
topsis_aarushi_102303601-1.0.0.dist-info/METADATA
topsis_aarushi_102303601-1.0.0.dist-info/WHEEL
topsis_aarushi_102303601-1.0.0.dist-info/entry_points.txt
topsis_aarushi_102303601-1.0.0.dist-info/top_level.txt
topsis_aarushi_102303601-1.0.0.dist-info/RECORD
