Metadata-Version: 2.4
Name: Topsis-Aarushi-102303601
Version: 1.0.0
Summary: TOPSIS implementation using Python
Author: Aarushi Rawal
Author-email: aarushirawal@gmail.com
Requires-Dist: numpy
Requires-Dist: pandas
Requires-Dist: openpyxl
Dynamic: author
Dynamic: author-email
Dynamic: description
Dynamic: description-content-type
Dynamic: requires-dist
Dynamic: summary
